{"cameraMode":{"drawMode":0,"name":"Shaded","section":"Shading Mode"},"sceneLighting":true,"audioPlay":false,"sceneViewState":{"m_AlwaysRefresh":false,"showFog":true,"showSkybox":true,"showFlares":true,"showImageEffects":true,"showParticleSystems":true,"showVisualEffectGraphs":true,"m_FxEnabled":true},"in2DMode":false,"pivot":{"x":-6.2106428146362309,"y":-5.113656044006348,"z":-18.03582000732422},"rotation":{"x":-0.03235376626253128,"y":0.9674184918403626,"z":-0.18806110322475434,"w":-0.16643136739730836},"size":11.375978469848633,"orthographic":false}